arshai/__init__.py
arshai/_version.py
arshai/agents/README.md
arshai/agents/__init__.py
arshai/agents/base.py
arshai/agents/hub/__init__.py
arshai/agents/hub/working_memory.py
arshai/cache/__init__.py
arshai/cache/decorators.py
arshai/clients/__init__.py
arshai/clients/redis_client.py
arshai/clients/safe_http_client.py
arshai/compat.py
arshai/config/__init__.py
arshai/config/config_loader.py
arshai/config/config_manager.py
arshai/core/__init__.py
arshai/core/interfaces/__init__.py
arshai/core/interfaces/iagent.py
arshai/core/interfaces/idocument.py
arshai/core/interfaces/idto.py
arshai/core/interfaces/iembedding.py
arshai/core/interfaces/illm.py
arshai/core/interfaces/imemorymanager.py
arshai/core/interfaces/inotification.py
arshai/core/interfaces/ireranker.py
arshai/core/interfaces/ivector_db_client.py
arshai/core/interfaces/iwebsearch.py
arshai/core/interfaces/iworkflow.py
arshai/core/interfaces/iworkflowrunner.py
arshai/embeddings/__init__.py
arshai/embeddings/cloudflare_gateway_embedding.py
arshai/embeddings/mgte_embeddings.py
arshai/embeddings/openai_embeddings.py
arshai/embeddings/voyageai_embedding.py
arshai/extensions/__init__.py
arshai/extensions/base.py
arshai/extensions/hooks.py
arshai/extensions/loader.py
arshai/llms/README.md
arshai/llms/__init__.py
arshai/llms/ai_gateway.py
arshai/llms/azure.py
arshai/llms/base_llm_client.py
arshai/llms/cloudflare_gateway.py
arshai/llms/google_genai.py
arshai/llms/openai.py
arshai/llms/openrouter.py
arshai/llms/utils/__init__.py
arshai/llms/utils/context_preparation.py
arshai/llms/utils/function_execution.py
arshai/llms/utils/json_processing.py
arshai/llms/utils/response_parsing.py
arshai/memory/__init__.py
arshai/memory/memory_types.py
arshai/memory/working_memory/__init__.py
arshai/memory/working_memory/in_memory_manager.py
arshai/memory/working_memory/redis_memory_manager.py
arshai/observability/MIGRATION_GUIDE.md
arshai/observability/README.md
arshai/observability/__init__.py
arshai/observability/config.py
arshai-1.8.0.dist-info/METADATA
arshai-1.8.0.dist-info/WHEEL
arshai-1.8.0.dist-info/licenses/LICENSE
arshai-1.8.0.dist-info/RECORD
