Metadata-Version: 2.4
Name: arshai
Version: 1.8.0
Summary: A powerful agent framework for building conversational AI systems
License: MIT
License-File: LICENSE
Keywords: ai,agents,llm,workflow,rag,conversational-ai,multi-agent,vector-db,embeddings
Author: Nima Nazarian
Author-email: nimunzn@gmail.com
Requires-Python: >=3.11,<3.13
Classifier: Development Status :: 4 - Beta
Classifier: Intended Audience :: Developers
Classifier: License :: OSI Approved :: MIT License
Classifier: Operating System :: OS Independent
Classifier: Programming Language :: Python :: 3
Classifier: Programming Language :: Python :: 3.11
Classifier: Programming Language :: Python :: 3.12
Classifier: Topic :: Scientific/Engineering :: Artificial Intelligence
Classifier: Topic :: Software Development :: Libraries :: Python Modules
Provides-Extra: docs
Provides-Extra: full
Provides-Extra: observability
Provides-Extra: production
Provides-Extra: rag
Provides-Extra: redis
Provides-Extra: reranking
Provides-Extra: vector-db
Provides-Extra: voyageai
Requires-Dist: aiohttp (>=3.11.16,<4.0.0)
Requires-Dist: flashrank (>=0.1.0,<0.2.0) ; extra == "reranking" or extra == "rag" or extra == "full"
Requires-Dist: furo (>=2023.9.10,<2024.0.0) ; extra == "docs"
Requires-Dist: google-auth (>=2.0.0,<3.0.0)
Requires-Dist: google-genai (>=1.25.0,<2.0.0)
Requires-Dist: loguru (>=0.7.3,<0.8.0)
Requires-Dist: mcp (>=1.10.1,<2.0.0)
Requires-Dist: myst-parser (>=2.0.0,<3.0.0) ; extra == "docs"
Requires-Dist: openai (>=1.0.0,<2.0.0)
Requires-Dist: opentelemetry-api (>=1.20.0,<2.0.0) ; extra == "observability" or extra == "full"
Requires-Dist: opentelemetry-exporter-otlp-proto-grpc (>=1.20.0,<2.0.0) ; extra == "observability" or extra == "full"
Requires-Dist: opentelemetry-exporter-otlp-proto-http (>=1.20.0,<2.0.0) ; extra == "observability" or extra == "full"
Requires-Dist: opentelemetry-sdk (>=1.20.0,<2.0.0) ; extra == "observability" or extra == "full"
Requires-Dist: pydantic (>=2.0.0,<3.0.0)
Requires-Dist: pymilvus (>=2.3.0,<3.0.0) ; extra == "vector-db" or extra == "rag" or extra == "full"
Requires-Dist: pyyaml (>=6.0.1,<7.0.0)
Requires-Dist: redis (>=5.0.0,<6.0.0) ; extra == "redis" or extra == "production" or extra == "full"
Requires-Dist: requests (>=2.32.3,<3.0.0)
Requires-Dist: sphinx (>=7.0.0,<8.0.0) ; extra == "docs"
Requires-Dist: sphinx-autodoc-typehints (>=1.24.0,<2.0.0) ; extra == "docs"
Requires-Dist: sphinx-copybutton (>=0.5.2,<0.6.0) ; extra == "docs"
Requires-Dist: sphinx-rtd-theme (>=2.0.0,<3.0.0) ; extra == "docs"
Requires-Dist: sphinxcontrib-mermaid (>=0.9.2,<0.10.0) ; extra == "docs"
Requires-Dist: voyageai (>=0.3.2,<0.4.0) ; extra == "voyageai" or extra == "full"
Project-URL: Documentation, https://arshai.readthedocs.io
Project-URL: Homepage, https://github.com/nimunzn/arshai
Project-URL: Repository, https://github.com/nimunzn/arshai
